mesop/__init__.py
mesop/example_index.py
mesop/version.py
mesop/bin/__init__.py
mesop/bin/bin.py
mesop/cli/__init__.py
mesop/cli/execute_module.py
mesop/colab/__init__.py
mesop/colab/colab_run.py
mesop/colab/colab_run_test.py
mesop/colab/colab_show.py
mesop/colab/colab_utils.py
mesop/commands/__init__.py
mesop/commands/navigate.py
mesop/commands/scroll_into_view.py
mesop/component_helpers/__init__.py
mesop/component_helpers/diff_component_test.py
mesop/component_helpers/helper.py
mesop/component_helpers/style.py
mesop/components/__init__.py
mesop/components/audio/__init__.py
mesop/components/audio/audio.py
mesop/components/audio/audio_pb2.py
mesop/components/audio/audio_pb2.pyi
mesop/components/audio/e2e/__init__.py
mesop/components/audio/e2e/audio_app.py
mesop/components/badge/__init__.py
mesop/components/badge/badge.py
mesop/components/badge/badge_pb2.py
mesop/components/badge/badge_pb2.pyi
mesop/components/badge/e2e/__init__.py
mesop/components/badge/e2e/badge_app.py
mesop/components/box/__init__.py
mesop/components/box/box.py
mesop/components/box/box_pb2.py
mesop/components/box/box_pb2.pyi
mesop/components/box/e2e/__init__.py
mesop/components/box/e2e/box_app.py
mesop/components/button/__init__.py
mesop/components/button/button.py
mesop/components/button/button_pb2.py
mesop/components/button/button_pb2.pyi
mesop/components/checkbox/__init__.py
mesop/components/checkbox/checkbox.py
mesop/components/checkbox/checkbox_pb2.py
mesop/components/checkbox/checkbox_pb2.pyi
mesop/components/checkbox/e2e/__init__.py
mesop/components/checkbox/e2e/checkbox_app.py
mesop/components/code/__init__.py
mesop/components/code/code.py
mesop/components/divider/__init__.py
mesop/components/divider/divider.py
mesop/components/divider/divider_pb2.py
mesop/components/divider/divider_pb2.pyi
mesop/components/divider/e2e/__init__.py
mesop/components/divider/e2e/divider_app.py
mesop/components/embed/__init__.py
mesop/components/embed/embed.py
mesop/components/embed/embed_pb2.py
mesop_rc-0.7.2rc0.dist-info/LICENSE
mesop_rc-0.7.2rc0.dist-info/METADATA
mesop_rc-0.7.2rc0.dist-info/WHEEL
mesop_rc-0.7.2rc0.dist-info/entry_points.txt
mesop_rc-0.7.2rc0.dist-info/top_level.txt
mesop_rc-0.7.2rc0.dist-info/RECORD
